interbreathe/__init__.py
interbreathe-0.1.0.dist-info/LICENSE
interbreathe-0.1.0.dist-info/METADATA
interbreathe-0.1.0.dist-info/WHEEL
interbreathe-0.1.0.dist-info/top_level.txt
interbreathe-0.1.0.dist-info/RECORD
